building_code_mcp/__init__.py
building_code_mcp/__main__.py
building_code_mcp/mcp_server.py
building_code_mcp-1.3.2.dist-info/licenses/LICENSE
maps/ABC2023.json
maps/BCBC2024.json
maps/IUGP9_2020.json
maps/NBC2025.json
maps/NECB2025.json
maps/NFC2025.json
maps/NPC2025.json
maps/OBC_Vol1.json
maps/OBC_Vol2.json
maps/OFC.json
maps/QCC2020.json
maps/QECB2020.json
maps/QPC2020.json
maps/QSC2020.json
maps/UGNECB_2020.json
maps/UGP4_2020.json
building_code_mcp-1.3.2.dist-info/METADATA
building_code_mcp-1.3.2.dist-info/WHEEL
building_code_mcp-1.3.2.dist-info/entry_points.txt
building_code_mcp-1.3.2.dist-info/top_level.txt
building_code_mcp-1.3.2.dist-info/RECORD
