Metadata-Version: 2.4
Name: building-code-mcp
Version: 1.3.2
Summary: MCP server for searching Canadian Building Codes (NBC, OBC, BCBC, etc.)
License: MIT
Project-URL: Homepage, https://github.com/your-username/building-code-mcp
Project-URL: Repository, https://github.com/your-username/building-code-mcp
Project-URL: Issues, https://github.com/your-username/building-code-mcp/issues
Keywords: mcp,building-code,canada,nbc,obc,claude
Classifier: Development Status :: 4 - Beta
Classifier: Intended Audience :: Developers
Classifier: License :: OSI Approved :: MIT License
Classifier: Programming Language :: Python :: 3
Classifier: Programming Language :: Python :: 3.10
Classifier: Programming Language :: Python :: 3.11
Classifier: Programming Language :: Python :: 3.12
Requires-Python: >=3.10
License-File: LICENSE
Requires-Dist: mcp>=0.1.0
Requires-Dist: rapidfuzz>=3.0.0
Provides-Extra: pdf
Requires-Dist: PyMuPDF>=1.23.0; extra == "pdf"
Provides-Extra: all
Requires-Dist: PyMuPDF>=1.23.0; extra == "all"
Requires-Dist: beautifulsoup4>=4.12.0; extra == "all"
Dynamic: license-file
